pyvd/__init__.py
pyvd/base.py
pyvd/constants.py
pyvd/version.py
pyvd/wpp.py
pyvd/data/WPP2022_FERT_F02_FERTILITY_RATES_BY_AGE_ESTIMATES.csv
pyvd/data/WPP2022_FERT_F02_FERTILITY_RATES_BY_AGE_MEDIUM_VARIANT.csv
pyvd/data/WPP2022_POP_F02_1_POPULATION_BY_AGE_BOTH_SEXES_ESTIMATES.csv
pyvd/data/WPP2022_POP_F02_1_POPULATION_BY_AGE_BOTH_SEXES_MEDIUM_VARIANT.csv
pyvd/data/__init__.py
pyvd/data/tlc_wpp_countries.json
pyvd/data/tlc_wpp_groups.json
pyvd/data/version.py
pyvd-1.0.1.dist-info/LICENSE
pyvd-1.0.1.dist-info/METADATA
pyvd-1.0.1.dist-info/WHEEL
pyvd-1.0.1.dist-info/top_level.txt
pyvd-1.0.1.dist-info/RECORD
