Metadata-Version: 2.2
Name: pyvd
Version: 1.0.1
Summary: Calculate birthrate and mortality from WPP data
Author: Katherine Rosenfeld, Kurt Frey
License: MIT License
Requires-Python: >=3.9
License-File: LICENSE
Requires-Dist: numpy>=1.0
